django_simple_ordering/__init__.py
django_simple_ordering/admin.py
django_simple_ordering/models.py
django_simple_ordering/locale/fa/LC_MESSAGES/django.mo
django_simple_ordering/locale/fa/LC_MESSAGES/django.po
django_simple_ordering/templates/django_simple_ordering/admin/ordering_regenerate_confirmation.html
django_simple_ordering-1.0.2.dist-info/licenses/LICENSE
django_simple_ordering-1.0.2.dist-info/METADATA
django_simple_ordering-1.0.2.dist-info/WHEEL
django_simple_ordering-1.0.2.dist-info/top_level.txt
django_simple_ordering-1.0.2.dist-info/RECORD
