Metadata-Version: 2.4
Name: django-simple-ordering
Version: 1.0.2
Summary: Simple Integer-based Ordering for Django Models
Author-email: Amin Vassefpoor <aminvassefpoor@gmail.com>
License-Expression: MIT
Project-URL: Homepage, https://github.com/aminvsf/django-simple-ordering
Project-URL: Issues, https://github.com/aminvsf/django-simple-ordering/issues
Classifier: Programming Language :: Python :: 3
Classifier: Operating System :: OS Independent
Requires-Python: >=3.9
License-File: LICENSE
Requires-Dist: django<6,>=4
Requires-Dist: django-object-actions<6,>=5
Provides-Extra: test
Requires-Dist: factory-boy<4,>=3; extra == "test"
Dynamic: license-file
